instaphyte/__init__.py
instaphyte/api.py
instaphyte/cli.py
instaphyte/iterators.py
instaphyte-1.1.1.dist-info/LICENSE
instaphyte-1.1.1.dist-info/METADATA
instaphyte-1.1.1.dist-info/WHEEL
instaphyte-1.1.1.dist-info/entry_points.txt
instaphyte-1.1.1.dist-info/top_level.txt
instaphyte-1.1.1.dist-info/RECORD
