Metadata-Version: 2.1
Name: instaphyte
Version: 1.1.1
Summary: Simple Instagram hashtag and location scraper
Home-page: https://github.com/scriptsmith/instaphyte
Author: Adam Smith
Author-email: adam.smith1@uq.edu.au
License: MIT
Keywords: instagram,instagram-scraper,instagram-api,socialreaper
Platform: UNKNOWN
Requires-Python: >=3.6
Requires-Dist: socialreaper
Requires-Dist: tqdm (==4.23.4)
